fxpy/__init__.py
fxpy/menu.py
fxpy/start.py
fxpy/web.py
fxpy-1.2.4.dist-info/licenses/LICENSE
fxpy-1.2.4.dist-info/METADATA
fxpy-1.2.4.dist-info/WHEEL
fxpy-1.2.4.dist-info/entry_points.txt
fxpy-1.2.4.dist-info/top_level.txt
fxpy-1.2.4.dist-info/RECORD
