Metadata-Version: 2.4
Name: FxPy
Version: 1.2.4
Summary: ForexPy: A currency conversion tool that also scraps the web and gives the Forex Exchange rates from major services.
Home-page: https://www.github.com/navrajkalsi/forexpy
Author: Navraj Singh Kalsi
Author-email: navrajkalsi@icloud.com
Classifier: Programming Language :: Python :: 3
Classifier: License :: OSI Approved :: MIT License
Classifier: Operating System :: OS Independent
Requires-Python: >=3.8
License-File: LICENSE
Requires-Dist: pycountry
Requires-Dist: requests
Requires-Dist: beautifulsoup4
Requires-Dist: keyboard
Requires-Dist: pandas
Requires-Dist: argparse
Requires-Dist: importlib.metadata
Dynamic: author
Dynamic: author-email
Dynamic: classifier
Dynamic: description
Dynamic: description-content-type
Dynamic: home-page
Dynamic: license-file
Dynamic: requires-dist
Dynamic: requires-python
Dynamic: summary
